{"turn": 20, "player": "One", "time": "2024-06-07T00:56:04M972", "currentShip": {"coords": "15;-4;-11", "passengers": 1, "direction": "Right"}, "otherShip": {"coords": "14;-3;-11", "passengers": 0, "direction": "UpRight"}, "data": [["-1;-2;3", {"fieldType": "Water", "hasStream": false, "segment": 0, "passengerDirection": null, "dock": false, "speed": 0, "nextDistance": 286, "nextDirection": "DownRight", "startDistance": 3, "startDirection": "DownRight", "meDistance": 158, "meDirection": "DownRight", "distanceScore": 0.0002108426638303914, "dockScore": 0.0002108426638303914}], ["-1;-1;2", {"fieldType": "Water", "hasStream": false, "segment": 0, "passengerDirection": null, "dock": false, "speed": 0, "nextDistance": 142, "nextDirection": "Right", "startDistance": 0, "startDirection": "Left", "meDistance": 78, "meDirection": "Right", "distanceScore": 0.0, "dockScore": 0.0}], ["-1;0;1", {"fieldType": "Water", "hasStream": true, "segment": 0, "passengerDirection": null, "dock": false, "speed": 0, "nextDistance": 143, "nextDirection": "Right", "startDistance": 2, "startDirection": "UpLeft", "meDistance": 79, "meDirection": "Right", "distanceScore": 0.0003748314023651403, "dockScore": 0.0003748314023651403}], ["-2;1;1", {"fieldType": "Water", "hasStream": false, "segment": 0, "passengerDirection": null, "dock": false, "speed": 0, "nextDistance": 145, "nextDirection": "Right", "startDistance": 6, "startDirection": "UpRight", "meDistance": 81, "meDirection": "Right", "distanceScore": 0.0032536943079679945, "dockScore": 0.0032536943079679945}], ["-3;2;1", {"fieldType": "Water", "hasStream": false, "segment": 0, "passengerDirection": null, "dock": false, "speed": 0, "nextDistance": 147, "nextDirection": "Right", "startDistance": 7, "startDirection": "UpRight", "meDistance": 83, "meDirection": "Right", "distanceScore": 0.004273891928100926, "dockScore": 0.004273891928100926}], ["0;-2;2", {"fieldType": "Water", "hasStream": false, "segment": 0, "passengerDirection": null, "dock": false, "speed": 0, "nextDistance": 284, "nextDirection": "DownRight", "startDistance": 2, "startDirection": "DownLeft", "meDistance": 156, "meDirection": "DownRight", "distanceScore": 9.543875963580882e-05, "dockScore": 9.543875963580882e-05}], ["0;-1;1", {"fieldType": "Water", "hasStream": false, "segment": 0, "passengerDirection": null, "dock": false, "speed": 0, "nextDistance": 141, "nextDirection": "Right", "startDistance": 1, "startDirection": "Left", "meDistance": 77, "meDirection": "Right", "distanceScore": 9.72165435415836e-05, "dockScore": 9.72165435415836e-05}], ["0;0;0", {"fieldType": "Water", "hasStream": true, "segment": 0, "passengerDirection": null, "dock": false, "speed": 0, "nextDistance": 142, "nextDirection": "Right", "startDistance": 4, "startDirection": "UpLeft", "meDistance": 78, "meDirection": "Right", "distanceScore": 0.0015270201541729412, "dockScore": 0.0015270201541729412}], ["-1;1;0", {"fieldType": "Water", "hasStream": false, "segment": 0, "passengerDirection": null, "dock": false, "speed": 0, "nextDistance": 144, "nextDirection": "Right", "startDistance": 3, "startDirection": "UpLeft", "meDistance": 80, "meDirection": "Right", "distanceScore": 0.0008282001201923076, "dockScore": 0.0008282001201923076}], ["-2;2;0", {"fieldType": "Water", "hasStream": false, "segment": 0, "passengerDirection": null, "dock": false, "speed": 0, "nextDistance": 146, "nextDirection": "Right", "startDistance": 8, "startDirection": "UpRight", "meDistance": 82, "meDirection": "Right", "distanceScore": 0.005681976307318385, "dockScore": 0.005681976307318385}], ["1;-2;1", {"fieldType": "Water", "hasStream": false, "segment": 0, "passengerDirection": null, "dock": false, "speed": 0, "nextDistance": 282, "nextDirection": "DownRight", "startDistance": 4, "startDirection": "DownLeft", "meDistance": 154, "meDirection": "DownRight", "distanceScore": 0.0003888661741663344, "dockScore": 0.0003888661741663344}], ["1;-1;0", {"fieldType": "Water", "hasStream": false, "segment": 0, "passengerDirection": null, "dock": false, "speed": 0, "nextDistance": 140, "nextDirection": "Right", "startDistance": 2, "startDirection": "Left", "meDistance": 76, "meDirection": "Right", "distanceScore": 0.00039617139959432054, "dockScore": 0.00039617139959432054}], ["1;0;-1", {"fieldType": "Water", "hasStream": true, "segment": 0, "passengerDirection": null, "dock": false, "speed": 0, "nextDistance": 141, "nextDirection": "Right", "startDistance": 6, "startDirection": "UpLeft", "meDistance": 77, "meDirection": "Right", "distanceScore": 0.0034997955674970094, "dockScore": 0.0034997955674970094}], ["0;1;-1", {"fieldType": "Water", "hasStream": false, "segment": 0, "passengerDirection": null, "dock": false, "speed": 0, "nextDistance": 143, "nextDirection": "Right", "startDistance": 5, "startDirection": "UpLeft", "meDistance": 79, "meDirection": "Right", "distanceScore": 0.002342696264782127, "dockScore": 0.002342696264782127}], ["-1;2;-1", {"fieldType": "Water", "hasStream": false, "segment": 0, "passengerDirection": null, "dock": false, "speed": 0, "nextDistance": 145, "nextDirection": "Right", "startDistance": 4, "startDirection": "UpLeft", "meDistance": 81, "meDirection": "Right", "distanceScore": 0.0014460863590968866, "dockScore": 0.0014460863590968866}], ["2;-2;0", {"fieldType": "Water", "hasStream": false, "segment": 0, "passengerDirection": null, "dock": false, "speed": 0, "nextDistance": 280, "nextDirection": "DownRight", "startDistance": 6, "startDirection": "DownLeft", "meDistance": 152, "meDirection": "DownRight", "distanceScore": 0.0008913856490872211, "dockScore": 0.0008913856490872211}], ["2;-1;-1", {"fieldType": "Water", "hasStream": false, "segment": 0, "passengerDirection": null, "dock": false, "speed": 0, "nextDistance": 139, "nextDirection": "Right", "startDistance": 3, "startDirection": "Left", "meDistance": 75, "meDirection": "Right", "distanceScore": 0.0009082745666644697, "dockScore": 0.0009082745666644697}], ["2;0;-2", {"fieldType": "Water", "hasStream": true, "segment": 0, "passengerDirection": null, "dock": false, "speed": 0, "nextDistance": 140, "nextDirection": "Right", "startDistance": 8, "startDirection": "UpLeft", "meDistance": 76, "meDirection": "Right", "distanceScore": 0.006338742393509129, "dockScore": 0.006338742393509129}], ["1;1;-2", {"fieldType": "Water", "hasStream": false, "segment": 0, "passengerDirection": null, "dock": false, "speed": 0, "nextDistance": 142, "nextDirection": "Right", "startDistance": 7, "startDirection": "UpLeft", "meDistance": 78, "meDirection": "Right", "distanceScore": 0.004676499222154632, "dockScore": 0.004676499222154632}], ["0;2;-2", {"fieldType": "Water", "hasStream": false, "segment": 0, "passengerDirection": null, "dock": false, "speed": 0, "nextDistance": 144, "nextDirection": "Right", "startDistance": 6, "startDirection": "UpLeft", "meDistance": 80, "meDirection": "Right", "distanceScore": 0.0033128004807692303, "dockScore": 0.0033128004807692303}], ["3;-2;-1", {"fieldType": "Water", "hasStream": false, "segment": 1, "passengerDirection": null, "dock": false, "speed": 0, "nextDistance": 278, "nextDirection": "DownRight", "startDistance": 8, "startDirection": "DownLeft", "meDistance": 150, "meDirection": "DownRight", "distanceScore": 0.0016147103407368351, "dockScore": 0.0016147103407368351}], ["3;-1;-2", {"fieldType": "Water", "hasStream": false, "segment": 1, "passengerDirection": null, "dock": false, "speed": 0, "nextDistance": 138, "nextDirection": "Right", "startDistance": 4, "startDirection": "Left", "meDistance": 74, "meDirection": "Right", "distanceScore": 0.0016455675797663696, "dockScore": 0.0016455675797663696}], ["3;0;-3", {"fieldType": "Water", "hasStream": true, "segment": 1, "passengerDirection": null, "dock": false, "speed": 0, "nextDistance": 69, "nextDirection": "UpRight", "startDistance": 10, "startDirection": "UpLeft", "meDistance": 37, "meDirection": "UpRight", "distanceScore": 0.04113918949415924, "dockScore": 0.04113918949415924}], ["2;1;-3", {"fieldType": "Water", "hasStream": false, "segment": 1, "passengerDirection": null, "dock": false, "speed": 0, "nextDistance": 70, "nextDirection": "UpRight", "startDistance": 9, "startDirection": "UpLeft", "meDistance": 38, "meDirection": "UpRight", "distanceScore": 0.032089883367139964, "dockScore": 0.032089883367139964}], ["1;2;-3", {"fieldType": "Water", "hasStream": false, "segment": 1, "passengerDirection": null, "dock": false, "speed": 0, "nextDistance": 71, "nextDirection": "UpRight", "startDistance": 8, "startDirection": "UpLeft", "meDistance": 39, "meDirection": "UpRight", "distanceScore": 0.02443232246676706, "dockScore": 0.02443232246676706}], ["4;-2;-2", {"fieldType": "Island", "hasStream": false, "segment": 1, "passengerDirection": null, "dock": false, "speed": 0, "nextDistance": 999999999999, "nextDirection": null, "startDistance": 999999999999, "startDirection": null, "meDistance": 999999999999, "meDirection": null, "distanceScore": -999999999999, "dockScore": -999999999999}], ["4;-1;-3", {"fieldType": "Water", "hasStream": false, "segment": 1, "passengerDirection": null, "dock": false, "speed": 0, "nextDistance": 68, "nextDirection": "UpRight", "startDistance": 5, "startDirection": "Left", "meDistance": 36, "meDirection": "UpRight", "distanceScore": 0.010686877456673217, "dockScore": 0.010686877456673217}], ["4;0;-4", {"fieldType": "Water", "hasStream": true, "segment": 1, "passengerDirection": null, "dock": false, "speed": 0, "nextDistance": 132, "nextDirection": "Right", "startDistance": 12, "startDirection": "UpLeft", "meDistance": 68, "meDirection": "Right", "distanceScore": 0.016649652056250904, "dockScore": 0.016649652056250904}], ["3;1;-4", {"fieldType": "Water", "hasStream": false, "segment": 1, "passengerDirection": null, "dock": false, "speed": 0, "nextDistance": 134, "nextDirection": "Right", "startDistance": 11, "startDirection": "UpLeft", "meDistance": 70, "meDirection": "Right", "distanceScore": 0.013445664005805517, "dockScore": 0.013445664005805517}], ["2;2;-4", {"fieldType": "Island", "hasStream": false, "segment": 1, "passengerDirection": null, "dock": false, "speed": 0, "nextDistance": 999999999999, "nextDirection": null, "startDistance": 999999999999, "startDirection": null, "meDistance": 999999999999, "meDirection": null, "distanceScore": -999999999999, "dockScore": -999999999999}], ["5;-2;-3", {"fieldType": "Water", "hasStream": false, "segment": 1, "passengerDirection": null, "dock": false, "speed": 0, "nextDistance": 33, "nextDirection": "Right", "startDistance": 12, "startDirection": "DownLeft", "meDistance": 17, "meDirection": "Right", "distanceScore": 0.26639443290001447, "dockScore": 0.26639443290001447}], ["5;-1;-4", {"fieldType": "Passenger", "hasStream": false, "segment": 1, "passengerDirection": null, "dock": false, "speed": 0, "nextDistance": 999999999999, "nextDirection": null, "startDistance": 999999999999, "startDirection": null, "meDistance": 999999999999, "meDirection": null, "distanceScore": -999999999999, "dockScore": -999999999999}], ["5;0;-5", {"fieldType": "Water", "hasStream": true, "segment": 1, "passengerDirection": null, "dock": false, "speed": 0, "nextDistance": 65, "nextDirection": "UpRight", "startDistance": 26, "startDirection": "Left", "meDistance": 33, "meDirection": "UpRight", "distanceScore": 0.3255396701596367, "dockScore": 0.3255396701596367}], ["4;1;-5", {"fieldType": "Water", "hasStream": false, "segment": 1, "passengerDirection": null, "dock": false, "speed": 0, "nextDistance": 66, "nextDirection": "UpRight", "startDistance": 13, "startDirection": "UpLeft", "meDistance": 34, "meDirection": "UpRight", "distanceScore": 0.07816086659740008, "dockScore": 0.07816086659740008}], ["3;2;-5", {"fieldType": "Water", "hasStream": false, "segment": 1, "passengerDirection": null, "dock": false, "speed": 0, "nextDistance": 67, "nextDirection": "UpRight", "startDistance": 12, "startDirection": "UpLeft", "meDistance": 35, "meDirection": "UpRight", "distanceScore": 0.06400580551523949, "dockScore": 0.06400580551523949}], ["6;-2;-4", {"fieldType": "Water", "hasStream": false, "segment": 1, "passengerDirection": null, "dock": false, "speed": 0, "nextDistance": 32, "nextDirection": "Right", "startDistance": 26, "startDirection": "Left", "meDistance": 16, "meDirection": "Right", "distanceScore": 1.3568647755872483, "dockScore": 1.3568647755872483}], ["6;-1;-5", {"fieldType": "Water", "hasStream": false, "segment": 1, "passengerDirection": null, "dock": false, "speed": 0, "nextDistance": 64, "nextDirection": "UpRight", "startDistance": 54, "startDirection": "DownLeft", "meDistance": 32, "meDirection": "UpRight", "distanceScore": 1.4632461855075503, "dockScore": 1.4632461855075503}], ["6;0;-6", {"fieldType": "Water", "hasStream": true, "segment": 1, "passengerDirection": null, "dock": false, "speed": 0, "nextDistance": 63, "nextDirection": "UpRight", "startDistance": 27, "startDirection": "Left", "meDistance": 31, "meDirection": "UpRight", "distanceScore": 0.3814676825184193, "dockScore": 0.3814676825184193}], ["5;1;-6", {"fieldType": "Water", "hasStream": false, "segment": 1, "passengerDirection": null, "dock": false, "speed": 0, "nextDistance": 64, "nextDirection": "UpRight", "startDistance": 28, "startDirection": "Left", "meDistance": 32, "meDirection": "UpRight", "distanceScore": 0.39341049706375836, "dockScore": 0.39341049706375836}], ["4;2;-6", {"fieldType": "Water", "hasStream": false, "segment": 1, "passengerDirection": null, "dock": false, "speed": 0, "nextDistance": 65, "nextDirection": "UpRight", "startDistance": 14, "startDirection": "UpLeft", "meDistance": 33, "meDirection": "UpRight", "distanceScore": 0.09438724164391833, "dockScore": 0.09438724164391833}], ["7;-2;-5", {"fieldType": "Water", "hasStream": false, "segment": 2, "passengerDirection": null, "dock": false, "speed": 0, "nextDistance": 31, "nextDirection": "Right", "startDistance": 27, "startDirection": "Left", "meDistance": 15, "meDirection": "Right", "distanceScore": 1.5924126248216832, "dockScore": 1.5924126248216832}], ["7;-1;-6", {"fieldType": "Water", "hasStream": false, "segment": 2, "passengerDirection": null, "dock": false, "speed": 0, "nextDistance": 62, "nextDirection": "UpRight", "startDistance": 56, "startDirection": "DownLeft", "meDistance": 30, "meDirection": "UpRight", "distanceScore": 1.7125534950071324, "dockScore": 1.7125534950071324}], ["7;0;-7", {"fieldType": "Water", "hasStream": true, "segment": 2, "passengerDirection": null, "dock": false, "speed": 0, "nextDistance": 61, "nextDirection": "UpRight", "startDistance": 28, "startDirection": "Left", "meDistance": 29, "meDirection": "UpRight", "distanceScore": 0.4471668876737638, "dockScore": 0.4471668876737638}], ["6;1;-7", {"fieldType": "Water", "hasStream": false, "segment": 2, "passengerDirection": null, "dock": false, "speed": 0, "nextDistance": 62, "nextDirection": "UpRight", "startDistance": 29, "startDirection": "Left", "meDistance": 30, "meDirection": "UpRight", "distanceScore": 0.4592657810271041, "dockScore": 0.4592657810271041}], ["5;2;-7", {"fieldType": "Water", "hasStream": false, "segment": 2, "passengerDirection": null, "dock": false, "speed": 0, "nextDistance": 63, "nextDirection": "UpRight", "startDistance": 30, "startDirection": "Left", "meDistance": 31, "meDirection": "UpRight", "distanceScore": 0.4709477561955794, "dockScore": 0.4709477561955794}], ["8;-2;-6", {"fieldType": "Water", "hasStream": false, "segment": 2, "passengerDirection": null, "dock": false, "speed": 0, "nextDistance": 30, "nextDirection": "Right", "startDistance": 28, "startDirection": "Left", "meDistance": 14, "meDirection": "Right", "distanceScore": 1.8697047096934962, "dockScore": 1.8697047096934962}], ["8;-1;-7", {"fieldType": "Water", "hasStream": false, "segment": 2, "passengerDirection": null, "dock": false, "speed": 0, "nextDistance": 60, "nextDirection": "UpRight", "startDistance": 58, "startDirection": "DownLeft", "meDistance": 28, "meDirection": "UpRight", "distanceScore": 2.005639873536008, "dockScore": 2.005639873536008}], ["8;0;-8", {"fieldType": "Island", "hasStream": true, "segment": 2, "passengerDirection": null, "dock": false, "speed": 0, "nextDistance": 999999999999, "nextDirection": null, "startDistance": 999999999999, "startDirection": null, "meDistance": 999999999999, "meDirection": null, "distanceScore": -999999999999, "dockScore": -999999999999}], ["7;1;-8", {"fieldType": "Water", "hasStream": false, "segment": 2, "passengerDirection": null, "dock": false, "speed": 0, "nextDistance": 115, "nextDirection": "Right", "startDistance": 30, "startDirection": "Left", "meDistance": 51, "meDirection": "Right", "distanceScore": 0.15042602286966736, "dockScore": 0.15042602286966736}], ["6;2;-8", {"fieldType": "Water", "hasStream": false, "segment": 2, "passengerDirection": null, "dock": false, "speed": 0, "nextDistance": 117, "nextDirection": "Right", "startDistance": 31, "startDirection": "Left", "meDistance": 53, "meDirection": "Right", "distanceScore": 0.15332730908211875, "dockScore": 0.15332730908211875}], ["9;-2;-7", {"fieldType": "Water", "hasStream": false, "segment": 2, "passengerDirection": null, "dock": false, "speed": 0, "nextDistance": 29, "nextDirection": "Right", "startDistance": 29, "startDirection": "Left", "meDistance": 13, "meDirection": "Right", "distanceScore": 2.19712900088719, "dockScore": 2.19712900088719}], ["9;-1;-8", {"fieldType": "Passenger", "hasStream": true, "segment": 2, "passengerDirection": null, "dock": false, "speed": 0, "nextDistance": 999999999999, "nextDirection": null, "startDistance": 999999999999, "startDirection": null, "meDistance": 999999999999, "meDirection": null, "distanceScore": -999999999999, "dockScore": -999999999999}], ["9;0;-9", {"fieldType": "Island", "hasStream": false, "segment": 2, "passengerDirection": null, "dock": false, "speed": 0, "nextDistance": 999999999999, "nextDirection": null, "startDistance": 999999999999, "startDirection": null, "meDistance": 999999999999, "meDirection": null, "distanceScore": -999999999999, "dockScore": -999999999999}], ["8;1;-9", {"fieldType": "Water", "hasStream": false, "segment": 2, "passengerDirection": null, "dock": false, "speed": 0, "nextDistance": 114, "nextDirection": "Right", "startDistance": 31, "startDirection": "Left", "meDistance": 50, "meDirection": "Right", "distanceScore": 0.1644536488600805, "dockScore": 0.1644536488600805}], ["7;2;-9", {"fieldType": "Water", "hasStream": false, "segment": 2, "passengerDirection": null, "dock": false, "speed": 0, "nextDistance": 116, "nextDirection": "Right", "startDistance": 32, "startDirection": "Left", "meDistance": 52, "meDirection": "Right", "distanceScore": 0.1672012557155531, "dockScore": 0.1672012557155531}], ["10;-2;-8", {"fieldType": "Water", "hasStream": true, "segment": 2, "passengerDirection": null, "dock": false, "speed": 0, "nextDistance": 28, "nextDirection": "Right", "startDistance": 30, "startDirection": "Left", "meDistance": 12, "meDirection": "Right", "distanceScore": 2.5850183823529416, "dockScore": 2.5850183823529416}], ["10;-1;-9", {"fieldType": "Water", "hasStream": false, "segment": 2, "passengerDirection": null, "dock": false, "speed": 0, "nextDistance": 56, "nextDirection": "UpRight", "startDistance": 62, "startDirection": "UpLeft", "meDistance": 24, "meDirection": "UpRight", "distanceScore": 2.76022518382353, "dockScore": 2.76022518382353}], ["10;0;-10", {"fieldType": "Water", "hasStream": false, "segment": 2, "passengerDirection": null, "dock": false, "speed": 0, "nextDistance": 55, "nextDirection": "UpRight", "startDistance": 63, "startDirection": "UpLeft", "meDistance": 23, "meDirection": "UpRight", "distanceScore": 2.992501551021212, "dockScore": 2.992501551021212}], ["9;1;-10", {"fieldType": "Water", "hasStream": false, "segment": 2, "passengerDirection": null, "dock": false, "speed": 0, "nextDistance": 56, "nextDirection": "UpRight", "startDistance": 32, "startDirection": "Left", "meDistance": 24, "meDirection": "UpRight", "distanceScore": 0.7352941176470589, "dockScore": 0.7352941176470589}], ["8;2;-10", {"fieldType": "Water", "hasStream": false, "segment": 2, "passengerDirection": null, "dock": false, "speed": 0, "nextDistance": 57, "nextDirection": "UpRight", "startDistance": 33, "startDirection": "Left", "meDistance": 25, "meDirection": "UpRight", "distanceScore": 0.7454319400983461, "dockScore": 0.7454319400983461}], ["9;-3;-6", {"fieldType": "Water", "hasStream": false, "segment": 3, "passengerDirection": null, "dock": false, "speed": 0, "nextDistance": 54, "nextDirection": "UpRight", "startDistance": 58, "startDirection": "DownLeft", "meDistance": 18, "meDirection": "UpRight", "distanceScore": 2.9011923267549786, "dockScore": 2.9011923267549786}], ["10;-3;-7", {"fieldType": "Passenger", "hasStream": false, "segment": 3, "passengerDirection": null, "dock": false, "speed": 0, "nextDistance": 999999999999, "nextDirection": null, "startDistance": 999999999999, "startDirection": null, "meDistance": 999999999999, "meDirection": null, "distanceScore": -999999999999, "dockScore": -999999999999}], ["11;-3;-8", {"fieldType": "Island", "hasStream": true, "segment": 3, "passengerDirection": null, "dock": false, "speed": 0, "nextDistance": 999999999999, "nextDirection": null, "startDistance": 999999999999, "startDirection": null, "meDistance": 999999999999, "meDirection": null, "distanceScore": -999999999999, "dockScore": -999999999999}], ["11;-2;-9", {"fieldType": "Water", "hasStream": false, "segment": 3, "passengerDirection": null, "dock": false, "speed": 0, "nextDistance": 27, "nextDirection": "Right", "startDistance": 31, "startDirection": "Left", "meDistance": 11, "meDirection": "Right", "distanceScore": 3.046144013413927, "dockScore": 3.046144013413927}], ["11;-1;-10", {"fieldType": "Water", "hasStream": false, "segment": 3, "passengerDirection": null, "dock": false, "speed": 0, "nextDistance": 54, "nextDirection": "UpRight", "startDistance": 64, "startDirection": "UpLeft", "meDistance": 22, "meDirection": "UpRight", "distanceScore": 3.2458391984764425, "dockScore": 3.2458391984764425}], ["10;-4;-6", {"fieldType": "Water", "hasStream": false, "segment": 3, "passengerDirection": null, "dock": false, "speed": 0, "nextDistance": 26, "nextDirection": "Right", "startDistance": 59, "startDirection": "DownLeft", "meDistance": 8, "meDirection": "Right", "distanceScore": 13.301759957077262, "dockScore": 13.301759957077262}], ["11;-4;-7", {"fieldType": "Water", "hasStream": false, "segment": 3, "passengerDirection": null, "dock": false, "speed": 0, "nextDistance": 25, "nextDirection": "Right", "startDistance": 120, "startDirection": "Left", "meDistance": 7, "meDirection": "Right", "distanceScore": 61.16165538666371, "dockScore": 61.16165538666371}], ["12;-4;-8", {"fieldType": "Water", "hasStream": true, "segment": 3, "passengerDirection": null, "dock": false, "speed": 0, "nextDistance": 24, "nextDirection": "Right", "startDistance": 121, "startDirection": "Left", "meDistance": 6, "meDirection": "Right", "distanceScore": 69.34864900395942, "dockScore": 69.34864900395942}], ["12;-3;-9", {"fieldType": "Water", "hasStream": false, "segment": 3, "passengerDirection": null, "dock": false, "speed": 0, "nextDistance": 48, "nextDirection": "UpRight", "startDistance": 64, "startDirection": "DownLeft", "meDistance": 12, "meDirection": "UpRight", "distanceScore": 4.8502845830240044, "dockScore": 4.8502845830240044}], ["12;-2;-10", {"fieldType": "Water", "hasStream": false, "segment": 3, "passengerDirection": null, "dock": false, "speed": 0, "nextDistance": 26, "nextDirection": "Right", "startDistance": 32, "startDirection": "Left", "meDistance": 10, "meDirection": "Right", "distanceScore": 3.5963302752293576, "dockScore": 3.5963302752293576}], ["11;-5;-6", {"fieldType": "Water", "hasStream": false, "segment": 3, "passengerDirection": null, "dock": false, "speed": 0, "nextDistance": 52, "nextDirection": "DownRight", "startDistance": 60, "startDirection": "DownLeft", "meDistance": 16, "meDirection": "DownRight", "distanceScore": 3.4391220802555402, "dockScore": 3.4391220802555402}], ["12;-5;-7", {"fieldType": "Water", "hasStream": false, "segment": 3, "passengerDirection": null, "dock": false, "speed": 0, "nextDistance": 50, "nextDirection": "DownRight", "startDistance": 122, "startDirection": "Left", "meDistance": 14, "meDirection": "DownRight", "distanceScore": 15.804341645401088, "dockScore": 15.804341645401088}], ["13;-5;-8", {"fieldType": "Water", "hasStream": false, "segment": 3, "passengerDirection": null, "dock": false, "speed": 0, "nextDistance": 48, "nextDirection": "DownRight", "startDistance": 123, "startDirection": "Left", "meDistance": 12, "meDirection": "DownRight", "distanceScore": 17.9150281876392, "dockScore": 17.9150281876392}], ["13;-4;-9", {"fieldType": "Water", "hasStream": true, "segment": 3, "passengerDirection": null, "dock": false, "speed": 0, "nextDistance": 23, "nextDirection": "Right", "startDistance": 65, "startDirection": "DownLeft", "meDistance": 5, "meDirection": "Right", "distanceScore": 22.38592128027682, "dockScore": 22.38592128027682}], ["13;-3;-10", {"fieldType": "Island", "hasStream": false, "segment": 3, "passengerDirection": null, "dock": false, "speed": 0, "nextDistance": 999999999999, "nextDirection": null, "startDistance": 999999999999, "startDirection": null, "meDistance": 999999999999, "meDirection": null, "distanceScore": -999999999999, "dockScore": -999999999999}], ["12;-6;-6", {"fieldType": "Water", "hasStream": false, "segment": 3, "passengerDirection": null, "dock": false, "speed": 0, "nextDistance": 51, "nextDirection": "DownRight", "startDistance": 61, "startDirection": "DownLeft", "meDistance": 15, "meDirection": "DownRight", "distanceScore": 3.7460757725180804, "dockScore": 3.7460757725180804}], ["13;-6;-7", {"fieldType": "Water", "hasStream": false, "segment": 3, "passengerDirection": null, "dock": false, "speed": 0, "nextDistance": 49, "nextDirection": "DownRight", "startDistance": 124, "startDirection": "Left", "meDistance": 13, "meDirection": "DownRight", "distanceScore": 17.23457675753228, "dockScore": 17.23457675753228}], ["14;-6;-8", {"fieldType": "Water", "hasStream": false, "segment": 3, "passengerDirection": null, "dock": false, "speed": 0, "nextDistance": 47, "nextDirection": "DownRight", "startDistance": 125, "startDirection": "Left", "meDistance": 11, "meDirection": "DownRight", "distanceScore": 19.56191030022566, "dockScore": 19.56191030022566}], ["14;-5;-9", {"fieldType": "Water", "hasStream": false, "segment": 3, "passengerDirection": null, "dock": false, "speed": 0, "nextDistance": 46, "nextDirection": "DownRight", "startDistance": 66, "startDirection": "DownLeft", "meDistance": 10, "meDirection": "DownRight", "distanceScore": 5.770004325259516, "dockScore": 5.770004325259516}], ["14;-4;-10", {"fieldType": "Water", "hasStream": true, "segment": 3, "passengerDirection": null, "dock": false, "speed": 0, "nextDistance": 22, "nextDirection": "Right", "startDistance": 132, "startDirection": "Left", "meDistance": 4, "meDirection": "Right", "distanceScore": 103.541213908724, "dockScore": 103.541213908724}], ["15;-6;-9", {"fieldType": "Water", "hasStream": false, "segment": 4, "passengerDirection": null, "dock": false, "speed": 0, "nextDistance": 94, "nextDirection": "DownLeft", "startDistance": 67, "startDirection": "DownLeft", "meDistance": 22, "meDirection": "DownLeft", "distanceScore": 1.4050146454034076, "dockScore": 1.4050146454034076}], ["15;-5;-10", {"fieldType": "Island", "hasStream": false, "segment": 4, "passengerDirection": null, "dock": false, "speed": 0, "nextDistance": 999999999999, "nextDirection": null, "startDistance": 999999999999, "startDirection": null, "meDistance": 999999999999, "meDirection": null, "distanceScore": -999999999999, "dockScore": -999999999999}], ["15;-4;-11", {"fieldType": "Water", "hasStream": true, "segment": 4, "passengerDirection": null, "dock": false, "speed": 0, "nextDistance": 10, "nextDirection": "UpRight", "startDistance": 69, "startDirection": "DownLeft", "meDistance": 0, "meDirection": "Left", "distanceScore": -999999999999, "dockScore": -999999999999}], ["14;-3;-11", {"fieldType": "Water", "hasStream": false, "segment": 4, "passengerDirection": null, "dock": false, "speed": 0, "nextDistance": 11, "nextDirection": "UpRight", "startDistance": 68, "startDirection": "DownLeft", "meDistance": 3, "meDirection": "UpRight", "distanceScore": 102.14223889209464, "dockScore": 102.14223889209464}], ["13;-2;-11", {"fieldType": "Water", "hasStream": false, "segment": 4, "passengerDirection": null, "dock": false, "speed": 0, "nextDistance": 12, "nextDirection": "UpRight", "startDistance": 33, "startDirection": "Left", "meDistance": 4, "meDirection": "UpRight", "distanceScore": 19.018376482664234, "dockScore": 19.018376482664234}], ["16;-6;-10", {"fieldType": "Island", "hasStream": false, "segment": 4, "passengerDirection": null, "dock": false, "speed": 0, "nextDistance": 999999999999, "nextDirection": null, "startDistance": 999999999999, "startDirection": null, "meDistance": 999999999999, "meDirection": null, "distanceScore": -999999999999, "dockScore": -999999999999}], ["16;-5;-11", {"fieldType": "Water", "hasStream": false, "segment": 4, "passengerDirection": null, "dock": false, "speed": 0, "nextDistance": 9, "nextDirection": "UpRight", "startDistance": 70, "startDirection": "DownLeft", "meDistance": 2, "meDirection": "DownLeft", "distanceScore": 168.91321476812243, "dockScore": 168.91321476812243}], ["16;-4;-12", {"fieldType": "Water", "hasStream": true, "segment": 4, "passengerDirection": null, "dock": false, "speed": 0, "nextDistance": 8, "nextDirection": "UpRight", "startDistance": 71, "startDirection": "DownLeft", "meDistance": 1, "meDirection": "Left", "distanceScore": 234.05188750758037, "dockScore": 234.05188750758037}], ["15;-3;-12", {"fieldType": "Water", "hasStream": false, "segment": 4, "passengerDirection": null, "dock": false, "speed": 0, "nextDistance": 9, "nextDirection": "UpRight", "startDistance": 70, "startDirection": "DownLeft", "meDistance": 2, "meDirection": "UpLeft", "distanceScore": 168.91321476812243, "dockScore": 168.91321476812243}], ["14;-2;-12", {"fieldType": "Water", "hasStream": false, "segment": 4, "passengerDirection": null, "dock": false, "speed": 0, "nextDistance": 10, "nextDirection": "UpRight", "startDistance": 34, "startDirection": "Left", "meDistance": 6, "meDirection": "UpRight", "distanceScore": 20.756625234521575, "dockScore": 20.756625234521575}], ["17;-6;-11", {"fieldType": "Water", "hasStream": false, "segment": 4, "passengerDirection": null, "dock": false, "speed": 0, "nextDistance": 8, "nextDirection": "UpRight", "startDistance": 71, "startDirection": "DownLeft", "meDistance": 3, "meDirection": "DownLeft", "distanceScore": 189.09924669279764, "dockScore": 189.09924669279764}], ["17;-5;-12", {"fieldType": "Water", "hasStream": true, "segment": 4, "passengerDirection": null, "dock": false, "speed": 0, "nextDistance": 7, "nextDirection": "UpRight", "startDistance": 72, "startDirection": "DownLeft", "meDistance": 4, "meDirection": "DownLeft", "distanceScore": 197.56097560975607, "dockScore": 197.56097560975607}], ["17;-4;-13", {"fieldType": "Water", "hasStream": false, "segment": 4, "passengerDirection": null, "dock": false, "speed": 0, "nextDistance": 6, "nextDirection": "UpRight", "startDistance": 73, "startDirection": "DownLeft", "meDistance": 2, "meDirection": "Left", "distanceScore": 372.2641993613139, "dockScore": 372.2641993613139}], ["16;-3;-13", {"fieldType": "Water", "hasStream": false, "segment": 4, "passengerDirection": null, "dock": false, "speed": 0, "nextDistance": 7, "nextDirection": "UpRight", "startDistance": 72, "startDirection": "DownLeft", "meDistance": 4, "meDirection": "UpLeft", "distanceScore": 197.56097560975607, "dockScore": 197.56097560975607}], ["15;-2;-13", {"fieldType": "Water", "hasStream": false, "segment": 4, "passengerDirection": null, "dock": false, "speed": 0, "nextDistance": 8, "nextDirection": "UpRight", "startDistance": 35, "startDirection": "Left", "meDistance": 3, "meDirection": "UpLeft", "distanceScore": 45.95250489955904, "dockScore": 45.95250489955904}], ["18;-6;-12", {"fieldType": "Water", "hasStream": true, "segment": 4, "passengerDirection": null, "dock": false, "speed": 0, "nextDistance": 6, "nextDirection": "UpRight", "startDistance": 73, "startDirection": "DownLeft", "meDistance": 5, "meDirection": "DownLeft", "distanceScore": 192.00073529411765, "dockScore": 192.00073529411765}], ["18;-5;-13", {"fieldType": "Water", "hasStream": false, "segment": 4, "passengerDirection": null, "dock": false, "speed": 0, "nextDistance": 5, "nextDirection": "UpRight", "startDistance": 74, "startDirection": "DownLeft", "meDistance": 6, "meDirection": "DownLeft", "distanceScore": 175.4944537463374, "dockScore": 175.4944537463374}], ["18;-4;-14", {"fieldType": "Water", "hasStream": false, "segment": 4, "passengerDirection": null, "dock": false, "speed": 0, "nextDistance": 12, "nextDirection": "UpLeft", "startDistance": 75, "startDirection": "DownLeft", "meDistance": 3, "meDirection": "Left", "distanceScore": 106.57363585746104, "dockScore": 106.57363585746104}], ["17;-3;-14", {"fieldType": "Water", "hasStream": false, "segment": 4, "passengerDirection": null, "dock": false, "speed": 0, "nextDistance": 14, "nextDirection": "UpLeft", "startDistance": 74, "startDirection": "DownLeft", "meDistance": 6, "meDirection": "UpLeft", "distanceScore": 62.91360294117648, "dockScore": 62.91360294117648}], ["16;-2;-14", {"fieldType": "Water", "hasStream": false, "segment": 4, "passengerDirection": null, "dock": false, "speed": 0, "nextDistance": 16, "nextDirection": "UpLeft", "startDistance": 36, "startDirection": "Left", "meDistance": 5, "meDirection": "UpLeft", "distanceScore": 13.013114754098362, "dockScore": 13.013114754098362}], ["17;-7;-10", {"fieldType": "Water", "hasStream": false, "segment": 5, "passengerDirection": null, "dock": false, "speed": 0, "nextDistance": 4, "nextDirection": "Right", "startDistance": 144, "startDirection": "DownRight", "meDistance": 8, "meDirection": "DownRight", "distanceScore": 448.9819004524886, "dockScore": 448.9819004524886}], ["18;-7;-11", {"fieldType": "Water", "hasStream": false, "segment": 5, "passengerDirection": null, "dock": false, "speed": 0, "nextDistance": 3, "nextDirection": "Right", "startDistance": 72, "startDirection": "DownLeft", "meDistance": 4, "meDirection": "DownLeft", "distanceScore": 393.3597621407333, "dockScore": 393.3597621407333}], ["19;-7;-12", {"fieldType": "Water", "hasStream": true, "segment": 5, "passengerDirection": null, "dock": false, "speed": 0, "nextDistance": 2, "nextDirection": "Right", "startDistance": 74, "startDirection": "DownLeft", "meDistance": 6, "meDirection": "DownLeft", "distanceScore": 224.92288090128756, "dockScore": 224.92288090128756}], ["19;-6;-13", {"fieldType": "Water", "hasStream": false, "segment": 5, "passengerDirection": null, "dock": false, "speed": 0, "nextDistance": 4, "nextDirection": "UpRight", "startDistance": 75, "startDirection": "DownLeft", "meDistance": 7, "meDirection": "DownLeft", "distanceScore": 153.753681720814, "dockScore": 153.753681720814}], ["19;-5;-14", {"fieldType": "Water", "hasStream": false, "segment": 5, "passengerDirection": null, "dock": false, "speed": 0, "nextDistance": 10, "nextDirection": "UpLeft", "startDistance": 76, "startDirection": "DownLeft", "meDistance": 8, "meDirection": "DownLeft", "distanceScore": 78.46433640880056, "dockScore": 78.46433640880056}], ["18;-8;-10", {"fieldType": "Water", "hasStream": false, "segment": 5, "passengerDirection": null, "dock": false, "speed": 0, "nextDistance": 8, "nextDirection": "DownRight", "startDistance": 146, "startDirection": "DownRight", "meDistance": 10, "meDirection": "DownRight", "distanceScore": 251.07788461538462, "dockScore": 251.07788461538462}], ["19;-8;-11", {"fieldType": "Island", "hasStream": false, "segment": 5, "passengerDirection": null, "dock": false, "speed": 0, "nextDistance": 999999999999, "nextDirection": null, "startDistance": 999999999999, "startDirection": null, "meDistance": 999999999999, "meDirection": null, "distanceScore": -999999999999, "dockScore": -999999999999}], ["20;-8;-12", {"fieldType": "Water", "hasStream": true, "segment": 5, "passengerDirection": null, "dock": false, "speed": 0, "nextDistance": 4, "nextDirection": "DownRight", "startDistance": 75, "startDirection": "DownLeft", "meDistance": 7, "meDirection": "DownLeft", "distanceScore": 153.753681720814, "dockScore": 153.753681720814}], ["20;-7;-13", {"fieldType": "Water", "hasStream": false, "segment": 5, "passengerDirection": null, "dock": false, "speed": 0, "nextDistance": 1, "nextDirection": "Right", "startDistance": 76, "startDirection": "DownLeft", "meDistance": 8, "meDirection": "DownLeft", "distanceScore": 139.90034799114204, "dockScore": 139.90034799114204}], ["20;-6;-14", {"fieldType": "Island", "hasStream": false, "segment": 5, "passengerDirection": null, "dock": false, "speed": 0, "nextDistance": 999999999999, "nextDirection": null, "startDistance": 999999999999, "startDirection": null, "meDistance": 999999999999, "meDirection": null, "distanceScore": -999999999999, "dockScore": -999999999999}], ["19;-9;-10", {"fieldType": "Island", "hasStream": false, "segment": 5, "passengerDirection": null, "dock": false, "speed": 0, "nextDistance": 999999999999, "nextDirection": null, "startDistance": 999999999999, "startDirection": null, "meDistance": 999999999999, "meDirection": null, "distanceScore": -999999999999, "dockScore": -999999999999}], ["20;-9;-11", {"fieldType": "Water", "hasStream": false, "segment": 5, "passengerDirection": null, "dock": false, "speed": 0, "nextDistance": 2, "nextDirection": "Right", "startDistance": 152, "startDirection": "DownRight", "meDistance": 16, "meDirection": "DownRight", "distanceScore": 139.90034799114204, "dockScore": 139.90034799114204}], ["21;-9;-12", {"fieldType": "Water", "hasStream": false, "segment": 5, "passengerDirection": null, "dock": false, "speed": 0, "nextDistance": 1, "nextDirection": "Right", "startDistance": 76, "startDirection": "DownLeft", "meDistance": 8, "meDirection": "DownLeft", "distanceScore": 139.90034799114204, "dockScore": 139.90034799114204}], ["21;-8;-13", {"fieldType": "Passenger", "hasStream": true, "segment": 5, "passengerDirection": "DownRight", "dock": false, "speed": 0, "nextDistance": 999999999999, "nextDirection": null, "startDistance": 999999999999, "startDirection": null, "meDistance": 999999999999, "meDirection": null, "distanceScore": -999999999999, "dockScore": -999999999999}], ["21;-7;-14", {"fieldType": "Water", "hasStream": false, "segment": 5, "passengerDirection": null, "dock": true, "speed": 1, "nextDistance": 0, "nextDirection": "Right", "startDistance": 154, "startDirection": "Left", "meDistance": 18, "meDirection": "Left", "distanceScore": 114.37114197530863, "dockScore": 88.24933794391097}], ["20;-10;-10", {"fieldType": "Water", "hasStream": false, "segment": 5, "passengerDirection": null, "dock": false, "speed": 0, "nextDistance": 2, "nextDirection": "Right", "startDistance": 153, "startDirection": "DownRight", "meDistance": 17, "meDirection": "DownRight", "distanceScore": 125.67502717200759, "dockScore": 125.67502717200759}], ["21;-10;-11", {"fieldType": "Water", "hasStream": false, "segment": 5, "passengerDirection": null, "dock": false, "speed": 0, "nextDistance": 1, "nextDirection": "Right", "startDistance": 154, "startDirection": "DownRight", "meDistance": 18, "meDirection": "DownRight", "distanceScore": 114.19132444500345, "dockScore": 114.19132444500345}], ["22;-10;-12", {"fieldType": "Water", "hasStream": false, "segment": 5, "passengerDirection": null, "dock": false, "speed": 0, "nextDistance": 0, "nextDirection": "Right", "startDistance": 77, "startDirection": "DownLeft", "meDistance": 9, "meDirection": "DownLeft", "distanceScore": 114.37114197530863, "dockScore": 114.37114197530863}], ["22;-9;-13", {"fieldType": "Water", "hasStream": false, "segment": 5, "passengerDirection": null, "dock": false, "speed": 0, "nextDistance": 0, "nextDirection": "Right", "startDistance": 154, "startDirection": "Left", "meDistance": 18, "meDirection": "Left", "distanceScore": 114.37114197530863, "dockScore": 114.37114197530863}], ["22;-8;-14", {"fieldType": "Water", "hasStream": true, "segment": 5, "passengerDirection": null, "dock": false, "speed": 0, "nextDistance": 0, "nextDirection": "Right", "startDistance": 310, "startDirection": "DownLeft", "meDistance": 38, "meDirection": "DownLeft", "distanceScore": 103.98632271468145, "dockScore": 103.98632271468145}]], "sortedGraph": [["17;-7;-10", {"fieldType": "Water", "hasStream": false, "segment": 5, "passengerDirection": null, "dock": false, "speed": 0, "nextDistance": 4, "nextDirection": "Right", "startDistance": 144, "startDirection": "DownRight", "meDistance": 8, "meDirection": "DownRight", "distanceScore": 448.9819004524886, "dockScore": 448.9819004524886}], ["18;-7;-11", {"fieldType": "Water", "hasStream": false, "segment": 5, "passengerDirection": null, "dock": false, "speed": 0, "nextDistance": 3, "nextDirection": "Right", "startDistance": 72, "startDirection": "DownLeft", "meDistance": 4, "meDirection": "DownLeft", "distanceScore": 393.3597621407333, "dockScore": 393.3597621407333}], ["17;-4;-13", {"fieldType": "Water", "hasStream": false, "segment": 4, "passengerDirection": null, "dock": false, "speed": 0, "nextDistance": 6, "nextDirection": "UpRight", "startDistance": 73, "startDirection": "DownLeft", "meDistance": 2, "meDirection": "Left", "distanceScore": 372.2641993613139, "dockScore": 372.2641993613139}], ["18;-8;-10", {"fieldType": "Water", "hasStream": false, "segment": 5, "passengerDirection": null, "dock": false, "speed": 0, "nextDistance": 8, "nextDirection": "DownRight", "startDistance": 146, "startDirection": "DownRight", "meDistance": 10, "meDirection": "DownRight", "distanceScore": 251.07788461538462, "dockScore": 251.07788461538462}], ["16;-4;-12", {"fieldType": "Water", "hasStream": true, "segment": 4, "passengerDirection": null, "dock": false, "speed": 0, "nextDistance": 8, "nextDirection": "UpRight", "startDistance": 71, "startDirection": "DownLeft", "meDistance": 1, "meDirection": "Left", "distanceScore": 234.05188750758037, "dockScore": 234.05188750758037}], ["19;-7;-12", {"fieldType": "Water", "hasStream": true, "segment": 5, "passengerDirection": null, "dock": false, "speed": 0, "nextDistance": 2, "nextDirection": "Right", "startDistance": 74, "startDirection": "DownLeft", "meDistance": 6, "meDirection": "DownLeft", "distanceScore": 224.92288090128756, "dockScore": 224.92288090128756}], ["17;-5;-12", {"fieldType": "Water", "hasStream": true, "segment": 4, "passengerDirection": null, "dock": false, "speed": 0, "nextDistance": 7, "nextDirection": "UpRight", "startDistance": 72, "startDirection": "DownLeft", "meDistance": 4, "meDirection": "DownLeft", "distanceScore": 197.56097560975607, "dockScore": 197.56097560975607}], ["16;-3;-13", {"fieldType": "Water", "hasStream": false, "segment": 4, "passengerDirection": null, "dock": false, "speed": 0, "nextDistance": 7, "nextDirection": "UpRight", "startDistance": 72, "startDirection": "DownLeft", "meDistance": 4, "meDirection": "UpLeft", "distanceScore": 197.56097560975607, "dockScore": 197.56097560975607}], ["18;-6;-12", {"fieldType": "Water", "hasStream": true, "segment": 4, "passengerDirection": null, "dock": false, "speed": 0, "nextDistance": 6, "nextDirection": "UpRight", "startDistance": 73, "startDirection": "DownLeft", "meDistance": 5, "meDirection": "DownLeft", "distanceScore": 192.00073529411765, "dockScore": 192.00073529411765}], ["17;-6;-11", {"fieldType": "Water", "hasStream": false, "segment": 4, "passengerDirection": null, "dock": false, "speed": 0, "nextDistance": 8, "nextDirection": "UpRight", "startDistance": 71, "startDirection": "DownLeft", "meDistance": 3, "meDirection": "DownLeft", "distanceScore": 189.09924669279764, "dockScore": 189.09924669279764}]], "sortedGraphDock": [["17;-7;-10", {"fieldType": "Water", "hasStream": false, "segment": 5, "passengerDirection": null, "dock": false, "speed": 0, "nextDistance": 4, "nextDirection": "Right", "startDistance": 144, "startDirection": "DownRight", "meDistance": 8, "meDirection": "DownRight", "distanceScore": 448.9819004524886, "dockScore": 448.9819004524886}], ["18;-7;-11", {"fieldType": "Water", "hasStream": false, "segment": 5, "passengerDirection": null, "dock": false, "speed": 0, "nextDistance": 3, "nextDirection": "Right", "startDistance": 72, "startDirection": "DownLeft", "meDistance": 4, "meDirection": "DownLeft", "distanceScore": 393.3597621407333, "dockScore": 393.3597621407333}], ["17;-4;-13", {"fieldType": "Water", "hasStream": false, "segment": 4, "passengerDirection": null, "dock": false, "speed": 0, "nextDistance": 6, "nextDirection": "UpRight", "startDistance": 73, "startDirection": "DownLeft", "meDistance": 2, "meDirection": "Left", "distanceScore": 372.2641993613139, "dockScore": 372.2641993613139}], ["18;-8;-10", {"fieldType": "Water", "hasStream": false, "segment": 5, "passengerDirection": null, "dock": false, "speed": 0, "nextDistance": 8, "nextDirection": "DownRight", "startDistance": 146, "startDirection": "DownRight", "meDistance": 10, "meDirection": "DownRight", "distanceScore": 251.07788461538462, "dockScore": 251.07788461538462}], ["16;-4;-12", {"fieldType": "Water", "hasStream": true, "segment": 4, "passengerDirection": null, "dock": false, "speed": 0, "nextDistance": 8, "nextDirection": "UpRight", "startDistance": 71, "startDirection": "DownLeft", "meDistance": 1, "meDirection": "Left", "distanceScore": 234.05188750758037, "dockScore": 234.05188750758037}], ["19;-7;-12", {"fieldType": "Water", "hasStream": true, "segment": 5, "passengerDirection": null, "dock": false, "speed": 0, "nextDistance": 2, "nextDirection": "Right", "startDistance": 74, "startDirection": "DownLeft", "meDistance": 6, "meDirection": "DownLeft", "distanceScore": 224.92288090128756, "dockScore": 224.92288090128756}], ["17;-5;-12", {"fieldType": "Water", "hasStream": true, "segment": 4, "passengerDirection": null, "dock": false, "speed": 0, "nextDistance": 7, "nextDirection": "UpRight", "startDistance": 72, "startDirection": "DownLeft", "meDistance": 4, "meDirection": "DownLeft", "distanceScore": 197.56097560975607, "dockScore": 197.56097560975607}], ["16;-3;-13", {"fieldType": "Water", "hasStream": false, "segment": 4, "passengerDirection": null, "dock": false, "speed": 0, "nextDistance": 7, "nextDirection": "UpRight", "startDistance": 72, "startDirection": "DownLeft", "meDistance": 4, "meDirection": "UpLeft", "distanceScore": 197.56097560975607, "dockScore": 197.56097560975607}], ["18;-6;-12", {"fieldType": "Water", "hasStream": true, "segment": 4, "passengerDirection": null, "dock": false, "speed": 0, "nextDistance": 6, "nextDirection": "UpRight", "startDistance": 73, "startDirection": "DownLeft", "meDistance": 5, "meDirection": "DownLeft", "distanceScore": 192.00073529411765, "dockScore": 192.00073529411765}], ["17;-6;-11", {"fieldType": "Water", "hasStream": false, "segment": 4, "passengerDirection": null, "dock": false, "speed": 0, "nextDistance": 8, "nextDirection": "UpRight", "startDistance": 71, "startDirection": "DownLeft", "meDistance": 3, "meDirection": "DownLeft", "distanceScore": 189.09924669279764, "dockScore": 189.09924669279764}]]}